Workbook

Sheet 01_Cuestionario
A1: No. | B1: Dimensión | C1: Pregunta | D1: A = Cat. 4 | E1: B = Cat. 3 | F1: C = Cat. 2 | G1: D = Cat. 1 | H1: Respuesta | I1: Puntaje | J1: Equivale a | K1: Peso dim. | L1: Aportación | M1: Acompañamiento asociado
A2: 1 | B2: Legal, fiscal y documentación institucional | C2: Situación legal y fiscal de la organización | D2: Está en proceso de formalización o tiene documentación legal/fiscal incompleta. | E2: Está constituida, pero su cumplimiento legal/fiscal es básico, reactivo o depende principalmente de terceros. | F2: Está constituida, cuenta con documentación actualizada y cumple regularmente sus obligaciones legales y fiscales. | G2: Tiene cumplimiento sistemático, revisión preventiva, políticas internas y capacidad para responder auditorías o requerimientos. | H2: D | I2: =IF(H2="","",IF(H2="A",1,IF(H2="B",2,IF(H2="C",3,IF(H2="D",4,""))))) -> 4 | J2: =IF(I2="","",IF(I2=1,"Categoría 4",IF(I2=2,"Categoría 3",IF(I2=3,"Categoría 2",IF(I2=4,"Categoría 1",""))))) -> Categoría 1 | K2: =IFERROR(VLOOKUP(B2,'05_Dimensiones'!$A$2:$B$9,2,FALSE),"") -> 0.25 | L2: =IF(I2="","",I2*K2/COUNTIF($B$2:$B$25,B2)) -> 0.33333333 | M2: Obligaciones fiscales y legales
A3: 2 | B3: Legal, fiscal y documentación institucional | C3: Administración y comprobación formal de recursos | D3: No cuenta con mecanismos formales para administrar o comprobar recursos; la evidencia es incompleta o dispersa. | E3: Administra recursos de forma básica, con controles manuales o apoyo externo, pero sin trazabilidad suficiente por proyecto. | F3: Cuenta con presupuestos, comprobación y conciliación regular de recursos por proyecto o fuente. | G3: Tiene controles internos, trazabilidad, conciliaciones periódicas y capacidad de responder a auditorías de forma ordenada. | H3: D | I3: =IF(H3="","",IF(H3="A",1,IF(H3="B",2,IF(H3="C",3,IF(H3="D",4,""))))) -> 4 | J3: =IF(I3="","",IF(I3=1,"Categoría 4",IF(I3=2,"Categoría 3",IF(I3=3,"Categoría 2",IF(I3=4,"Categoría 1",""))))) -> Categoría 1 | K3: =IFERROR(VLOOKUP(B3,'05_Dimensiones'!$A$2:$B$9,2,FALSE),"") -> 0.25 | L3: =IF(I3="","",I3*K3/COUNTIF($B$2:$B$25,B3)) -> 0.33333333 | M3: Obligaciones fiscales y legales / Movilización de recursos
A4: 3 | B4: Legal, fiscal y documentación institucional | C4: Archivo legal, fiscal y administrativo | D4: La documentación está dispersa, incompleta o desactualizada. | E4: Cuenta con documentos básicos, pero el archivo depende de personas específicas o no se actualiza de forma periódica. | F4: Mantiene archivo legal, fiscal y administrativo actualizado, organizado y disponible. | G4: Cuenta con gestión documental institucional, responsables definidos y revisión periódica de vigencia y cumplimiento. | H4: D | I4: =IF(H4="","",IF(H4="A",1,IF(H4="B",2,IF(H4="C",3,IF(H4="D",4,""))))) -> 4 | J4: =IF(I4="","",IF(I4=1,"Categoría 4",IF(I4=2,"Categoría 3",IF(I4=3,"Categoría 2",IF(I4=4,"Categoría 1",""))))) -> Categoría 1 | K4: =IFERROR(VLOOKUP(B4,'05_Dimensiones'!$A$2:$B$9,2,FALSE),"") -> 0.25 | L4: =IF(I4="","",I4*K4/COUNTIF($B$2:$B$25,B4)) -> 0.33333333 | M4: Transparencia y buenas prácticas
A5: 4 | B5: Gobernanza y toma de decisiones | C5: Funcionamiento del órgano de gobierno | D5: No cuenta con órgano de gobierno activo o las decisiones se toman principalmente de forma operativa e informal. | E5: Cuenta con órgano de gobierno formal, pero su participación es limitada, principalmente de validación o firma. | F5: El órgano de gobierno sesiona, toma acuerdos y revisa temas estratégicos, legales y financieros. | G5: El órgano de gobierno participa activamente en estrategia, supervisión de resultados, riesgos y crecimiento institucional. | H5: D | I5: =IF(H5="","",IF(H5="A",1,IF(H5="B",2,IF(H5="C",3,IF(H5="D",4,""))))) -> 4 | J5: =IF(I5="","",IF(I5=1,"Categoría 4",IF(I5=2,"Categoría 3",IF(I5=3,"Categoría 2",IF(I5=4,"Categoría 1",""))))) -> Categoría 1 | K5: =IFERROR(VLOOKUP(B5,'05_Dimensiones'!$A$2:$B$9,2,FALSE),"") -> 0.15 | L5: =IF(I5="","",I5*K5/COUNTIF($B$2:$B$25,B5)) -> 0.2 | M5: Gobernanza / Estructura del órgano de gobierno
A6: 5 | B6: Gobernanza y toma de decisiones | C6: Claridad de roles entre consejo/patronato y dirección | D6: Los roles no están diferenciados o dependen de acuerdos informales. | E6: Existen roles generales, pero se mezclan funciones estratégicas, operativas y administrativas. | F6: Las funciones están definidas y se respetan en la mayoría de las decisiones relevantes. | G6: Existe una arquitectura clara de gobernanza, con comités, responsabilidades, seguimiento y rendición de cuentas. | H6: D | I6: =IF(H6="","",IF(H6="A",1,IF(H6="B",2,IF(H6="C",3,IF(H6="D",4,""))))) -> 4 | J6: =IF(I6="","",IF(I6=1,"Categoría 4",IF(I6=2,"Categoría 3",IF(I6=3,"Categoría 2",IF(I6=4,"Categoría 1",""))))) -> Categoría 1 | K6: =IFERROR(VLOOKUP(B6,'05_Dimensiones'!$A$2:$B$9,2,FALSE),"") -> 0.15 | L6: =IF(I6="","",I6*K6/COUNTIF($B$2:$B$25,B6)) -> 0.2 | M6: Gobernanza
A7: 6 | B7: Gobernanza y toma de decisiones | C7: Documentación y seguimiento de decisiones | D7: Las decisiones relevantes no se documentan o se registran de manera informal. | E7: Se documentan algunas decisiones, pero no hay seguimiento sistemático de acuerdos. | F7: Las decisiones se documentan mediante actas, minutas o acuerdos y se da seguimiento regular. | G7: Existe un sistema institucional de seguimiento de acuerdos, riesgos y decisiones estratégicas. | H7: D | I7: =IF(H7="","",IF(H7="A",1,IF(H7="B",2,IF(H7="C",3,IF(H7="D",4,""))))) -> 4 | J7: =IF(I7="","",IF(I7=1,"Categoría 4",IF(I7=2,"Categoría 3",IF(I7=3,"Categoría 2",IF(I7=4,"Categoría 1",""))))) -> Categoría 1 | K7: =IFERROR(VLOOKUP(B7,'05_Dimensiones'!$A$2:$B$9,2,FALSE),"") -> 0.15 | L7: =IF(I7="","",I7*K7/COUNTIF($B$2:$B$25,B7)) -> 0.2 | M7: Gobernanza / Transparencia
A8: 7 | B8: Planeación e identidad institucional | C8: Claridad de misión, visión y líneas de trabajo | D8: La organización opera con una misión general no formalizada o poco conocida por el equipo. | E8: Tiene misión/visión o prioridades, pero no orientan de manera clara las decisiones cotidianas. | F8: Cuenta con misión, visión, objetivos y líneas de trabajo claras, conocidas por el equipo. | G8: La identidad institucional orienta decisiones, alianzas, comunicación, programas y crecimiento estratégico. | H8: D | I8: =IF(H8="","",IF(H8="A",1,IF(H8="B",2,IF(H8="C",3,IF(H8="D",4,""))))) -> 4 | J8: =IF(I8="","",IF(I8=1,"Categoría 4",IF(I8=2,"Categoría 3",IF(I8=3,"Categoría 2",IF(I8=4,"Categoría 1",""))))) -> Categoría 1 | K8: =IFERROR(VLOOKUP(B8,'05_Dimensiones'!$A$2:$B$9,2,FALSE),"") -> 0.15 | L8: =IF(I8="","",I8*K8/COUNTIF($B$2:$B$25,B8)) -> 0.2 | M8: Planeación estratégica
A9: 8 | B9: Planeación e identidad institucional | C9: Planeación estratégica o plan institucional | D9: No cuenta con planeación escrita; opera principalmente por urgencias u oportunidades. | E9: Cuenta con una planeación básica o desactualizada que se consulta ocasionalmente. | F9: Tiene planeación vigente con objetivos, metas y líneas de acción definidas. | G9: Tiene planeación estratégica viva, revisada periódicamente y ajustada con evidencia/contexto. | H9: D | I9: =IF(H9="","",IF(H9="A",1,IF(H9="B",2,IF(H9="C",3,IF(H9="D",4,""))))) -> 4 | J9: =IF(I9="","",IF(I9=1,"Categoría 4",IF(I9=2,"Categoría 3",IF(I9=3,"Categoría 2",IF(I9=4,"Categoría 1",""))))) -> Categoría 1 | K9: =IFERROR(VLOOKUP(B9,'05_Dimensiones'!$A$2:$B$9,2,FALSE),"") -> 0.15 | L9: =IF(I9="","",I9*K9/COUNTIF($B$2:$B$25,B9)) -> 0.2 | M9: Planeación estratégica
A10: 9 | B10: Planeación e identidad institucional | C10: Traducción de la estrategia a planes operativos | D10: No hay planes operativos claros con responsables, actividades y tiempos. | E10: Existen actividades planeadas, pero no siempre se vinculan a metas o responsables claros. | F10: Cuenta con planes operativos, responsables, cronogramas y metas vinculadas a la estrategia. | G10: Integra planeación estratégica, presupuesto, operación, indicadores y aprendizaje institucional. | H10: D | I10: =IF(H10="","",IF(H10="A",1,IF(H10="B",2,IF(H10="C",3,IF(H10="D",4,""))))) -> 4 | J10: =IF(I10="","",IF(I10=1,"Categoría 4",IF(I10=2,"Categoría 3",IF(I10=3,"Categoría 2",IF(I10=4,"Categoría 1",""))))) -> Categoría 1 | K10: =IFERROR(VLOOKUP(B10,'05_Dimensiones'!$A$2:$B$9,2,FALSE),"") -> 0.15 | L10: =IF(I10="","",I10*K10/COUNTIF($B$2:$B$25,B10)) -> 0.2 | M10: Planeación estratégica / Diseño de proyectos
A11: 10 | B11: Administración, operación y talento | C11: Estructura interna y distribución de responsabilidades | D11: La estructura es informal y depende de pocas personas clave. | E11: Existe una estructura básica, pero con roles poco claros o alta concentración de funciones. | F11: Cuenta con organigrama, roles y responsabilidades definidos para la operación principal. | G11: Tiene estructura funcional, perfiles, procesos de coordinación y capacidad para escalar operación. | H11: D | I11: =IF(H11="","",IF(H11="A",1,IF(H11="B",2,IF(H11="C",3,IF(H11="D",4,""))))) -> 4 | J11: =IF(I11="","",IF(I11=1,"Categoría 4",IF(I11=2,"Categoría 3",IF(I11=3,"Categoría 2",IF(I11=4,"Categoría 1",""))))) -> Categoría 1 | K11: =IFERROR(VLOOKUP(B11,'05_Dimensiones'!$A$2:$B$9,2,FALSE),"") -> 0.1 | L11: =IF(I11="","",I11*K11/COUNTIF($B$2:$B$25,B11)) -> 0.13333333 | M11: Gobernanza / Transparencia
A12: 11 | B12: Administración, operación y talento | C12: Gestión del equipo, voluntariado o colaboraciones | D12: Las colaboraciones son informales y no hay procesos claros de incorporación o seguimiento. | E12: Existen acuerdos básicos de colaboración, pero sin gestión sistemática del talento. | F12: Cuenta con procesos para incorporación, funciones, capacitación o seguimiento del equipo. | G12: Tiene políticas de talento, desarrollo de capacidades, evaluación y sucesión de roles clave. | H12: D | I12: =IF(H12="","",IF(H12="A",1,IF(H12="B",2,IF(H12="C",3,IF(H12="D",4,""))))) -> 4 | J12: =IF(I12="","",IF(I12=1,"Categoría 4",IF(I12=2,"Categoría 3",IF(I12=3,"Categoría 2",IF(I12=4,"Categoría 1",""))))) -> Categoría 1 | K12: =IFERROR(VLOOKUP(B12,'05_Dimensiones'!$A$2:$B$9,2,FALSE),"") -> 0.1 | L12: =IF(I12="","",I12*K12/COUNTIF($B$2:$B$25,B12)) -> 0.13333333 | M12: Transparencia y buenas prácticas
A13: 12 | B13: Administración, operación y talento | C13: Procesos administrativos y control interno | D13: Los procesos administrativos se resuelven caso por caso, sin criterios comunes. | E13: Existen procedimientos básicos, pero se aplican de forma irregular o dependen de una persona. | F13: Tiene procedimientos para compras, pagos, archivos, comprobaciones y control interno. | G13: Cuenta con procesos institucionalizados, supervisión, mejora continua y gestión de riesgos operativos. | H13: D | I13: =IF(H13="","",IF(H13="A",1,IF(H13="B",2,IF(H13="C",3,IF(H13="D",4,""))))) -> 4 | J13: =IF(I13="","",IF(I13=1,"Categoría 4",IF(I13=2,"Categoría 3",IF(I13=3,"Categoría 2",IF(I13=4,"Categoría 1",""))))) -> Categoría 1 | K13: =IFERROR(VLOOKUP(B13,'05_Dimensiones'!$A$2:$B$9,2,FALSE),"") -> 0.1 | L13: =IF(I13="","",I13*K13/COUNTIF($B$2:$B$25,B13)) -> 0.13333333 | M13: Obligaciones fiscales y legales / Gestión de riesgos
... A25: 24 | B25: Evaluación, impacto e innovación | C25: Innovación, herramientas digitales y mejora continua | D25: Usa herramientas digitales básicas solo para operación cotidiana. | E25: Ha incorporado algunas herramientas, pero sin estrategia clara de transformación digital o innovación. | F25: Utiliza herramientas digitales, datos o nuevas metodologías para mejorar operación y proyectos. | G25: Integra innovación, análisis de datos, IA o transformación digital para escalar impacto y eficiencia. | H25: D | I25: =IF(H25="","",IF(H25="A",1,IF(H25="B",2,IF(H25="C",3,IF(H25="D",4,""))))) -> 4 | J25: =IF(I25="","",IF(I25=1,"Categoría 4",IF(I25=2,"Categoría 3",IF(I25=3,"Categoría 2",IF(I25=4,"Categoría 1",""))))) -> Categoría 1 | K25: =IFERROR(VLOOKUP(B25,'05_Dimensiones'!$A$2:$B$9,2,FALSE),"") -> 0.05 | L25: =IF(I25="","",I25*K25/COUNTIF($B$2:$B$25,B25)) -> 0.066666667 | M25: IA y transformación digital / Innovación institucional

Sheet 02_Resultados
A1: Resultado del autodiagnóstico | ¿a qué categoría se manda la OSC?
A3: Nombre de la organización
A4: Municipio / Estado
A5: Persona que responde
A6: Cargo
A7: Fecha
A8: Respuestas capturadas | B8: =(COUNTIF('01_Cuestionario'!H2:H25,"A")+COUNTIF('01_Cuestionario'!H2:H25,"B")+COUNTIF('01_Cuestionario'!H2:H25,"C")+COUNTIF('01_Cuestionario'!H2:H25,"D"))&" de 24" -> 24 de 24
A9: Puntaje ponderado | B9: =IF((COUNTIF('01_Cuestionario'!H2:H25,"A")+COUNTIF('01_Cuestionario'!H2:H25,"B")+COUNTIF('01_Cuestionario'!H2:H25,"C")+COUNTIF('01_Cuestionario'!H2:H25,"D"))<24,"Pendiente",SUM('01_Cuestionario'!L2:L25)) -> 4
A10: Categoría final | B10: =IF(B9="Pendiente","Pendiente",IF(B9<=1.75,"Categoría 4",IF(B9<=2.5,"Categoría 3",IF(B9<=3.25,"Categoría 2","Categoría 1")))) -> Categoría 1
A13: Dimensión | B13: Promedio | C13: Categoría predominante | D13: Peso | E13: Aportación ponderada
A14: Legal, fiscal y documentación institucional | B14: =IFERROR(AVERAGEIF('01_Cuestionario'!$B$2:$B$25,A14,'01_Cuestionario'!$I$2:$I$25),"") -> 4 | C14: =IF(B14="","Pendiente",IF(B14<=1.75,"Categoría 4",IF(B14<=2.5,"Categoría 3",IF(B14<=3.25,"Categoría 2","Categoría 1")))) -> Categoría 1 | D14: =VLOOKUP(A14,'05_Dimensiones'!$A$2:$B$9,2,FALSE) -> 0.25 | E14: =IFERROR(SUMIFS('01_Cuestionario'!$L$2:$L$25,'01_Cuestionario'!$B$2:$B$25,A14),"") -> 1
A15: Gobernanza y toma de decisiones | B15: =IFERROR(AVERAGEIF('01_Cuestionario'!$B$2:$B$25,A15,'01_Cuestionario'!$I$2:$I$25),"") -> 4 | C15: =IF(B15="","Pendiente",IF(B15<=1.75,"Categoría 4",IF(B15<=2.5,"Categoría 3",IF(B15<=3.25,"Categoría 2","Categoría 1")))) -> Categoría 1 | D15: =VLOOKUP(A15,'05_Dimensiones'!$A$2:$B$9,2,FALSE) -> 0.15 | E15: =IFERROR(SUMIFS('01_Cuestionario'!$L$2:$L$25,'01_Cuestionario'!$B$2:$B$25,A15),"") -> 0.6
A16: Planeación e identidad institucional | B16: =IFERROR(AVERAGEIF('01_Cuestionario'!$B$2:$B$25,A16,'01_Cuestionario'!$I$2:$I$25),"") -> 4 | C16: =IF(B16="","Pendiente",IF(B16<=1.75,"Categoría 4",IF(B16<=2.5,"Categoría 3",IF(B16<=3.25,"Categoría 2","Categoría 1")))) -> Categoría 1 | D16: =VLOOKUP(A16,'05_Dimensiones'!$A$2:$B$9,2,FALSE) -> 0.15 | E16: =IFERROR(SUMIFS('01_Cuestionario'!$L$2:$L$25,'01_Cuestionario'!$B$2:$B$25,A16),"") -> 0.6
A17: Administración, operación y talento | B17: =IFERROR(AVERAGEIF('01_Cuestionario'!$B$2:$B$25,A17,'01_Cuestionario'!$I$2:$I$25),"") -> 4 | C17: =IF(B17="","Pendiente",IF(B17<=1.75,"Categoría 4",IF(B17<=2.5,"Categoría 3",IF(B17<=3.25,"Categoría 2","Categoría 1")))) -> Categoría 1 | D17: =VLOOKUP(A17,'05_Dimensiones'!$A$2:$B$9,2,FALSE) -> 0.1 | E17: =IFERROR(SUMIFS('01_Cuestionario'!$L$2:$L$25,'01_Cuestionario'!$B$2:$B$25,A17),"") -> 0.4
A18: Diseño y gestión de proyectos | B18: =IFERROR(AVERAGEIF('01_Cuestionario'!$B$2:$B$25,A18,'01_Cuestionario'!$I$2:$I$25),"") -> 4 | C18: =IF(B18="","Pendiente",IF(B18<=1.75,"Categoría 4",IF(B18<=2.5,"Categoría 3",IF(B18<=3.25,"Categoría 2","Categoría 1")))) -> Categoría 1 | D18: =VLOOKUP(A18,'05_Dimensiones'!$A$2:$B$9,2,FALSE) -> 0.1 | E18: =IFERROR(SUMIFS('01_Cuestionario'!$L$2:$L$25,'01_Cuestionario'!$B$2:$B$25,A18),"") -> 0.4
A19: Sostenibilidad financiera y movilización de recursos | B19: =IFERROR(AVERAGEIF('01_Cuestionario'!$B$2:$B$25,A19,'01_Cuestionario'!$I$2:$I$25),"") -> 4 | C19: =IF(B19="","Pendiente",IF(B19<=1.75,"Categoría 4",IF(B19<=2.5,"Categoría 3",IF(B19<=3.25,"Categoría 2","Categoría 1")))) -> Categoría 1 | D19: =VLOOKUP(A19,'05_Dimensiones'!$A$2:$B$9,2,FALSE) -> 0.1 | E19: =IFERROR(SUMIFS('01_Cuestionario'!$L$2:$L$25,'01_Cuestionario'!$B$2:$B$25,A19),"") -> 0.4
A20: Comunicación, alianzas y transparencia | B20: =IFERROR(AVERAGEIF('01_Cuestionario'!$B$2:$B$25,A20,'01_Cuestionario'!$I$2:$I$25),"") -> 4 | C20: =IF(B20="","Pendiente",IF(B20<=1.75,"Categoría 4",IF(B20<=2.5,"Categoría 3",IF(B20<=3.25,"Categoría 2","Categoría 1")))) -> Categoría 1 | D20: =VLOOKUP(A20,'05_Dimensiones'!$A$2:$B$9,2,FALSE) -> 0.1 | E20: =IFERROR(SUMIFS('01_Cuestionario'!$L$2:$L$25,'01_Cuestionario'!$B$2:$B$25,A20),"") -> 0.4
A21: Evaluación, impacto e innovación | B21: =IFERROR(AVERAGEIF('01_Cuestionario'!$B$2:$B$25,A21,'01_Cuestionario'!$I$2:$I$25),"") -> 4 | C21: =IF(B21="","Pendiente",IF(B21<=1.75,"Categoría 4",IF(B21<=2.5,"Categoría 3",IF(B21<=3.25,"Categoría 2","Categoría 1")))) -> Categoría 1 | D21: =VLOOKUP(A21,'05_Dimensiones'!$A$2:$B$9,2,FALSE) -> 0.05 | E21: =IFERROR(SUMIFS('01_Cuestionario'!$L$2:$L$25,'01_Cuestionario'!$B$2:$B$25,A21),"") -> 0.2
A24: Interpretación rápida
A26: =IF($B$10="Pendiente","Faltan respuestas.","Resultado: "&$B$10&_xlfn._LONGTEXT(". Esta categoría se obtiene sin candados externos: cada respuesta ya incluye el nivel de formalización, cumplimiento y madurez correspondiente. El promedio ponderado favorece legal/fiscal, gobernanza y planeación para evitar que comunicación o alianzas el","even artificialmente la clasificación.")) -> Resultado: Categoría 1. Esta categoría se obtiene sin candados externos: cada respuesta ya incluye el nivel de formalización, cumplimiento y madurez correspondiente. El promedio ponderado favorece legal/fiscal, gobernanza y planeación para evitar que comunicación o alianzas eleven artificialmente la clasificación.

Sheet 03_Escalas
A1: Equivalencias de respuesta y categoría final
A3: Respuesta | B3: Puntaje | C3: Categoría equivalente | D3: Nombre de la categoría | E3: Interpretación
A4: A | B4: 1 | C4: 4 | D4: Impulso a OSC emergentes | E4: Estructura incipiente, procesos no formalizados o en formalización.
A5: B | B5: 2 | C5: 3 | D5: Construcción y consolidación de capacidades | E5: Operación básica, con áreas que requieren profesionalización.
A6: C | B6: 3 | C6: 2 | D6: Innovación institucional | E6: Institucionalización funcional, con procesos y programas más consolidados.
A7: D | B7: 4 | C7: 1 | D7: Escalamiento e impacto transformador | E7: Prácticas sistemáticas, medición, sostenibilidad y capacidad de incidencia/escalamiento.
A10: Puntaje ponderado | B10: Categoría final | C10: Nombre | D10: A dónde se manda
A11: 1.00 a 1.75 | B11: 4 | C11: Impulso a OSC emergentes | D11: Plan genérico de Categoría 4
A12: 1.76 a 2.50 | B12: 3 | C12: Construcción y consolidación de capacidades | D12: Plan genérico de Categoría 3
A13: 2.51 a 3.25 | B13: 2 | C13: Innovación institucional | D13: Plan genérico de Categoría 2
A14: 3.26 a 4.00 | B14: 1 | C14: Escalamiento e impacto transformador | D14: Plan genérico de Categoría 1

Sheet 05_Dimensiones
A1: Dimensión | B1: Peso | C1: Peso % | D1: Número de reactivos | E1: Qué define
A2: Legal, fiscal y documentación institucional | B2: 0.25 | C2: 25% | D2: 3 | E2: La posibilidad real de operar, recibir/comprobar recursos y sostener cumplimiento institucional.
A3: Gobernanza y toma de decisiones | B3: 0.15 | C3: 15% | D3: 3 | E3: Funcionamiento del consejo/patronato/asamblea, roles y supervisión estratégica.
A4: Planeación e identidad institucional | B4: 0.15 | C4: 15% | D4: 3 | E4: Claridad de misión, estrategia, metas y uso de la planeación para decidir.
A5: Administración, operación y talento | B5: 0.1 | C5: 10% | D5: 3 | E5: Estructura, procesos administrativos, roles y gestión del equipo.
A6: Diseño y gestión de proyectos | B6: 0.1 | C6: 10% | D6: 3 | E6: Capacidad para diseñar, ejecutar y dar seguimiento técnico a proyectos.
A7: Sostenibilidad financiera y movilización de recursos | B7: 0.1 | C7: 10% | D7: 3 | E7: Presupuesto, flujo, diversificación y procuración/movilización de recursos.
A8: Comunicación, alianzas y transparencia | B8: 0.1 | C8: 10% | D8: 3 | E8: Comunicación institucional, redes, grupos de interés y rendición de cuentas.
A9: Evaluación, impacto e innovación | B9: 0.05 | C9: 5% | D9: 3 | E9: Registro de información, indicadores, aprendizaje, herramientas digitales e innovación.
